ecom_finder/__init__.py
ecom_finder-1.0.2.dist-info/LICENSE
ecom_finder-1.0.2.dist-info/METADATA
ecom_finder-1.0.2.dist-info/WHEEL
ecom_finder-1.0.2.dist-info/top_level.txt
ecom_finder-1.0.2.dist-info/RECORD
