Metadata-Version: 2.1
Name: ecom-finder
Version: 1.0.2
Summary: Python based library to find any product in ecommerce site using crawling and AI (like audio, images)
Home-page: https://github.com/MYGITHUBPRIYANKA/ecom_finder
Author: Priyanka Das
Author-email: mymailid.priyanka@gmail.com
License: MIT License
Platform: UNKNOWN
License-File: LICENSE
Requires-Dist: bs4
Requires-Dist: pandas
Requires-Dist: requests
Requires-Dist: SpeechRecognition
Requires-Dist: pyaudio
